dgcv/CR_geometry.py
dgcv/Riemannian_geometry.py
dgcv/__init__.py
dgcv/_config.py
dgcv/_dgcv_display.py
dgcv/_safeguards.py
dgcv/_settings.py
dgcv/_tables.py
dgcv/_tensor_field_printers.py
dgcv/base.py
dgcv/combinatorics.py
dgcv/complex_structures.py
dgcv/conversions.py
dgcv/coordinate_maps.py
dgcv/dgcv_core.py
dgcv/dgcv_formatter.py
dgcv/filtered_structures.py
dgcv/light_wrappers.py
dgcv/morphisms.py
dgcv/polynomials.py
dgcv/solvers.py
dgcv/styles.py
dgcv/tensors.py
dgcv/vector_fields_and_differential_forms.py
dgcv/vmf.py
dgcv/algebras/__init__.py
dgcv/algebras/algebras_aux.py
dgcv/algebras/algebras_core.py
dgcv/algebras/algebras_secondary.py
dgcv/assets/__init__.py
dgcv/assets/fonts/Orbitron-Black.ttf
dgcv/assets/fonts/Orbitron-Black.woff2
dgcv/assets/fonts/Orbitron-Bold.ttf
dgcv/assets/fonts/Orbitron-Bold.woff2
dgcv/assets/fonts/Orbitron-ExtraBold.ttf
dgcv/assets/fonts/Orbitron-ExtraBold.woff2
dgcv/assets/fonts/Orbitron-Medium.ttf
dgcv/assets/fonts/Orbitron-Medium.woff2
dgcv/assets/fonts/Orbitron-Regular.ttf
dgcv/assets/fonts/Orbitron-Regular.woff2
dgcv/assets/fonts/Orbitron-SemiBold.ttf
dgcv/assets/fonts/Orbitron-SemiBold.woff2
dgcv/assets/fonts/PatrickHand-Regular.ttf
dgcv/assets/fonts/fonts.css
dgcv/backends/__init__.py
dgcv/backends/_caches.py
dgcv/backends/_sage_backend.py
dgcv/backends/_symbolic_api.py
dgcv/eds/__init__.py
dgcv/eds/abst_vector_fields.py
dgcv/eds/ast.py
dgcv/eds/eds.py
dgcv/eds/eds_operations.py
dgcv/eds/eds_representations.py
dgcv-0.3.12.dist-info/licenses/LICENSE.txt
dgcv-0.3.12.dist-info/METADATA
dgcv-0.3.12.dist-info/WHEEL
dgcv-0.3.12.dist-info/top_level.txt
dgcv-0.3.12.dist-info/RECORD
