Metadata-Version: 2.4
Name: dgcv
Version: 0.3.12
Summary: Differential Geometry with Complex Variables
Author: David Sykes
Author-email: David Sykes <david@realandimaginary.com>
License: MIT
Requires-Python: >=3.9
License-File: LICENSE.txt
Requires-Dist: sympy>=1.9
Requires-Dist: ipython>=7.0
Dynamic: license-file
Dynamic: requires-python
